hyperstellar/__init__.py
hyperstellar/__init__.pyi
hyperstellar/py.typed
hyperstellar/_native/windows-x64/stellar.pyd
hyperstellar/_native/windows-x64/shaders/math.comp
hyperstellar/_native/windows-x64/shaders/quad.frag
hyperstellar/_native/windows-x64/shaders/quad.geom
hyperstellar/_native/windows-x64/shaders/quad.vert
hyperstellar-0.1.43.dist-info/licenses/LICENSE
hyperstellar-0.1.43.dist-info/METADATA
hyperstellar-0.1.43.dist-info/WHEEL
hyperstellar-0.1.43.dist-info/top_level.txt
hyperstellar-0.1.43.dist-info/RECORD
