Metadata-Version: 2.4
Name: hyperstellar
Version: 0.1.43
Summary: GPU-accelerated physics simulation engine
Author-email: Aiden Jabari <Jabariaiden15@email.com>
License: <<<<<<< HEAD
Keywords: physics,simulation,gpu,opengl
Classifier: Development Status :: 3 - Alpha
Classifier: Intended Audience :: Science/Research
Classifier: License :: OSI Approved :: MIT License
Classifier: Operating System :: Microsoft :: Windows
Classifier: Programming Language :: Python :: 3.13
Classifier: Topic :: Scientific/Engineering :: Physics
Requires-Python: >=3.13
License-File: LICENSE
Dynamic: license-file
